{
  "deckname": "Arena 09-05 10:06",
  "deckguid": "dfc0c36c-924e-4f94-9ac5-250516828e9a",
  "detectedheroes": [],
  "pickedhero": "Hunter",
  "detectedcards": [
    {
      "Item1": "UNG_801",
      "Item2": "CFM_646",
      "Item3": "EX1_583"
    },
    {
      "Item1": "OG_326",
      "Item2": "CFM_120",
      "Item3": "OG_158"
    },
    {
      "Item1": "OG_326",
      "Item2": "CFM_120",
      "Item3": "OG_158"
    },
    {
      "Item1": "EX1_283",
      "Item2": "OG_326",
      "Item3": "UNG_910"
    },
    {
      "Item1": "CFM_654",
      "Item2": "EX1_617",
      "Item3": "KAR_029"
    },
    {
      "Item1": "EX1_162",
      "Item2": "OG_249",
      "Item3": "CFM_039"
    },
    {
      "Item1": "UNG_084",
      "Item2": "UNG_814",
      "Item3": "DS1_070"
    },
    {
      "Item1": "CS2_155",
      "Item2": "EX1_611",
      "Item3": "OG_179"
    },
    {
      "Item1": "UNG_083",
      "Item2": "OG_216",
      "Item3": "CFM_688"
    },
    {
      "Item1": "NEW1_017",
      "Item2": "OG_272",
      "Item3": "UNG_847"
    },
    {
      "Item1": "OG_152",
      "Item2": "NEW1_022",
      "Item3": "EX1_028"
    },
    {
      "Item1": "OG_248",
      "Item2": "EX1_610",
      "Item3": "OG_158"
    },
    {
      "Item1": "CFM_328",
      "Item2": "UNG_087",
      "Item3": "UNG_848"
    },
    {
      "Item1": "UNG_010",
      "Item2": "CS2_119",
      "Item3": "EX1_538"
    },
    {
      "Item1": "CS2_117",
      "Item2": "OG_150",
      "Item3": "OG_295"
    },
    {
      "Item1": "KAR_005",
      "Item2": "CFM_665",
      "Item3": "OG_151"
    },
    {
      "Item1": "CS2_141",
      "Item2": "UNG_813",
      "Item3": "CFM_334"
    },
    {
      "Item1": "OG_327",
      "Item2": "EX1_556",
      "Item3": "EX1_531"
    },
    {
      "Item1": "OG_292",
      "Item2": "CFM_658",
      "Item3": "CFM_338"
    },
    {
      "Item1": "EX1_537",
      "Item2": "EX1_006",
      "Item3": "KAR_037"
    },
    {
      "Item1": "CFM_665",
      "Item2": "EX1_506",
      "Item3": "UNG_910"
    },
    {
      "Item1": "KAR_005",
      "Item2": "UNG_928",
      "Item3": "OG_256"
    },
    {
      "Item1": "UNG_914",
      "Item2": "CFM_335",
      "Item3": "KAR_041"
    },
    {
      "Item1": "NEW1_025",
      "Item2": "OG_034",
      "Item3": "KAR_004"
    },
    {
      "Item1": "EX1_008",
      "Item2": "EX1_538",
      "Item3": "UNG_910"
    },
    {
      "Item1": "EX1_610",
      "Item2": "DS1_184",
      "Item3": "CFM_654"
    },
    {
      "Item1": "OG_337",
      "Item2": "OG_174",
      "Item3": "EX1_549"
    },
    {
      "Item1": "UNG_812",
      "Item2": "CS2_151",
      "Item3": "CS2_117"
    },
    {
      "Item1": "EX1_007",
      "Item2": "UNG_818",
      "Item3": "EX1_538"
    },
    {
      "Item1": "NEW1_021",
      "Item2": "OG_308",
      "Item3": "UNG_113"
    }
  ],
  "cardrating": [
    {
      "Item1": 78.0,
      "Item2": 98.0,
      "Item3": 70.0
    },
    {
      "Item1": 93.0,
      "Item2": 78.0,
      "Item3": 130.0
    },
    {
      "Item1": 103.0,
      "Item2": 122.0,
      "Item3": 57.0
    },
    {
      "Item1": 121.0,
      "Item2": 89.0,
      "Item3": 31.0
    },
    {
      "Item1": 111.0,
      "Item2": 143.0,
      "Item3": 107.0
    },
    {
      "Item1": 88.0,
      "Item2": 136.0,
      "Item3": 91.0
    },
    {
      "Item1": 59.0,
      "Item2": 118.0,
      "Item3": 110.0
    },
    {
      "Item1": 82.0,
      "Item2": 106.0,
      "Item3": 108.0
    },
    {
      "Item1": 75.0,
      "Item2": 75.0,
      "Item3": 116.0
    },
    {
      "Item1": 56.0,
      "Item2": 107.0,
      "Item3": 70.0
    },
    {
      "Item1": 85.0,
      "Item2": 122.0,
      "Item3": 141.0
    },
    {
      "Item1": 114.0,
      "Item2": 92.0,
      "Item3": 125.0
    },
    {
      "Item1": 96.0,
      "Item2": 101.0,
      "Item3": 88.0
    },
    {
      "Item1": 133.0,
      "Item2": 94.0,
      "Item3": 72.0
    },
    {
      "Item1": 79.0,
      "Item2": 88.0,
      "Item3": 74.0
    },
    {
      "Item1": 85.0,
      "Item2": 100.0,
      "Item3": 100.0
    },
    {
      "Item1": 91.0,
      "Item2": 97.0,
      "Item3": 135.0
    },
    {
      "Item1": 151.0,
      "Item2": 35.0,
      "Item3": 84.0
    },
    {
      "Item1": 94.0,
      "Item2": 110.0,
      "Item3": 130.0
    },
    {
      "Item1": 133.0,
      "Item2": 128.0,
      "Item3": 64.0
    },
    {
      "Item1": 82.0,
      "Item2": 119.0,
      "Item3": 84.0
    },
    {
      "Item1": 73.0,
      "Item2": 53.0,
      "Item3": 108.0
    },
    {
      "Item1": 97.0,
      "Item2": 125.0,
      "Item3": 130.0
    },
    {
      "Item1": 107.0,
      "Item2": 107.0,
      "Item3": 103.0
    },
    {
      "Item1": 103.0,
      "Item2": 96.0,
      "Item3": 63.0
    },
    {
      "Item1": 108.0,
      "Item2": 110.0,
      "Item3": 96.0
    },
    {
      "Item1": 109.0,
      "Item2": 107.0,
      "Item3": 125.0
    },
    {
      "Item1": 78.0,
      "Item2": 122.0,
      "Item3": 100.0
    }
  ],
  "pickedcards": [
    "CFM_120",
    "UNG_910",
    "EX1_617",
    "EX1_162",
    "UNG_814",
    "EX1_611",
    "OG_216",
    "OG_272",
    "EX1_028",
    "EX1_610",
    "UNG_848",
    "EX1_538",
    "OG_150",
    "KAR_005",
    "UNG_813",
    "EX1_531",
    "CFM_338",
    "EX1_537",
    "UNG_910",
    "KAR_005",
    "CFM_335",
    "KAR_004",
    "EX1_538",
    "DS1_184",
    "OG_337",
    "UNG_812",
    "EX1_007",
    "OG_308"
  ]
}